{
  "ETH-USD": {
    "m": "ETH-USD",
    "t": 1678924889,
    "c": "1677.10",
    "h": "1693.92",
    "l": "1638.49",
    "o": "1656.12"
  },
  "MATIC-USD": {
    "m": "MATIC-USD",
    "t": 1678924800,
    "c": "1.15023",
    "h": "1.15846",
    "l": "1.10210",
    "o": "1.11593"
  },
  "BTC-USD": {
    "m": "BTC-USD",
    "t": 1678924800,
    "c": "25053.00",
    "h": "25207.00",
    "l": "24216.01",
    "o": "24369.31"
  },
  "NEAR-USD": {
    "m": "NEAR-USD",
    "t": 1678924800,
    "c": "1.96599",
    "h": "1.98300",
    "l": "1.89700",
    "o": "1.92461"
  },
  "SOL-USD": {
    "m": "SOL-USD",
    "t": 1678924800,
    "c": "19.72",
    "h": "19.93",
    "l": "18.95",
    "o": "19.31"
  },
  "XAU-USD": {
    "m": "XAU-USD",
    "t": 1678924800,
    "c": "1921.45",
    "h": "1933.39",
    "l": "1907.62",
    "o": "1921.20"
  },
  "USD-CHF": {
    "m": "USD-CHF",
    "t": 1678924800,
    "c": "0.92928",
    "h": "0.93224",
    "l": "0.92299",
    "o": "0.93155"
  },
  "USD-CNH": {
    "m": "USD-CNH",
    "t": 1678924800,
    "c": "6.89432",
    "h": "6.91382",
    "l": "6.88486",
    "o": "6.89057"
  },
  "USD-JPY": {
    "m": "USD-JPY",
    "t": 1678924800,
    "c": "133.38",
    "h": "133.83",
    "l": "131.73",
    "o": "132.91"
  },
  "AUD-USD": {
    "m": "AUD-USD",
    "t": 1678924800,
    "c": "0.66634",
    "h": "0.66667",
    "l": "0.66139",
    "o": "0.66175"
  },
  "GBP-USD": {
    "m": "GBP-USD",
    "t": 1678924800,
    "c": "1.21093",
    "h": "1.21278",
    "l": "1.20290",
    "o": "1.20679"
  },
  "NZD-USD": {
    "m": "NZD-USD",
    "t": 1678924800,
    "c": "0.62036",
    "h": "0.62058",
    "l": "0.61457",
    "o": "0.61612"
  },
  "USD-ZAR": {
    "m": "USD-ZAR",
    "t": 1678924800,
    "c": "18.40",
    "h": "18.46",
    "l": "18.27",
    "o": "18.38"
  },
  "XAG-USD": {
    "m": "XAG-USD",
    "t": 1678924800,
    "c": "21.74",
    "h": "22.09",
    "l": "21.47",
    "o": "21.81"
  },
  "BNB-USD": {
    "m": "BNB-USD",
    "t": 1678924800,
    "c": "329.81",
    "h": "332.92",
    "l": "303.39",
    "o": "307.02"
  },
  "AAVE-USD": {
    "m": "AAVE-USD",
    "t": 1678924800,
    "c": "74.95",
    "h": "75.80",
    "l": "73.25",
    "o": "74.09"
  },
  "ADA-USD": {
    "m": "ADA-USD",
    "t": 1678924800,
    "c": "0.32550",
    "h": "0.32977",
    "l": "0.31828",
    "o": "0.32526"
  },
  "USD-SGD": {
    "m": "USD-SGD",
    "t": 1678924800,
    "c": "1.34607",
    "h": "1.35176",
    "l": "1.34577",
    "o": "1.35145"
  },
  "USD-CAD": {
    "m": "USD-CAD",
    "t": 1678924800,
    "c": "1.37205",
    "h": "1.37871",
    "l": "1.37144",
    "o": "1.37679"
  },
  "USD-MXN": {
    "m": "USD-MXN",
    "t": 1678924800,
    "c": "18.78",
    "h": "19.18",
    "l": "18.70",
    "o": "19.01"
  },
  "EUR-USD": {
    "m": "EUR-USD",
    "t": 1678924800,
    "c": "1.06139",
    "h": "1.06446",
    "l": "1.05523",
    "o": "1.05820"
  },
  "QQQ-USD": {
    "m": "QQQ-USD",
    "t": 1678924800,
    "c": "306.44",
    "h": "307.12",
    "l": "297.25",
    "o": "297.87"
  },
  "SPY-USD": {
    "m": "SPY-USD",
    "t": 1678924800,
    "c": "395.89",
    "h": "396.40",
    "l": "386.31",
    "o": "386.80"
  }
}